Metadata-Version: 1.2
Name: calc20
Version: 0.0.4
Summary: 生成60道20以内数字减法运算题
Home-page: UNKNOWN
Author: Yarving Liu
Author-email: yarving@qq.com
License: GNU General Public License v3
Keywords: calc20
Platform: UNKNOWN
Classifier: Development Status :: 2 - Pre-Alpha
Classifier: Intended Audience :: Developers
Classifier: License :: OSI Approved :: GNU General Public License v3 (GPLv3)
Classifier: Natural Language :: English
Classifier: Programming Language :: Python :: 3
Classifier: Programming Language :: Python :: 3.5
Classifier: Programming Language :: Python :: 3.6
Classifier: Programming Language :: Python :: 3.7
Classifier: Programming Language :: Python :: 3.8
Requires-Python: >=3.7
